RcTorch/__init__.py
RcTorch/clustering.py
RcTorch/custom_loss.py
RcTorch/defs.py
RcTorch/esn.py
RcTorch/esn_cv.py
RcTorch/esn_orig.py
RcTorch/hesn.py
RcTorch/old_backprop_code.py
RcTorch/scr.py
rctorch-private/__init__.py
rctorch-private/clustering.py
rctorch-private/custom_loss.py
rctorch-private/defs.py
rctorch-private/esn.py
rctorch-private/esn_cv.py
rctorch-private/esn_orig.py
rctorch-private/hesn.py
rctorch-private/old_backprop_code.py
rctorch-private/scr.py
rctorch_private-0.9800.dist-info/AUTHORS
rctorch_private-0.9800.dist-info/LICENSE.txt
rctorch_private-0.9800.dist-info/METADATA
rctorch_private-0.9800.dist-info/WHEEL
rctorch_private-0.9800.dist-info/top_level.txt
rctorch_private-0.9800.dist-info/RECORD
