Metadata-Version: 2.1
Name: rctorch-private
Version: 0.9800
Summary: A Python 3 toolset for creating and optimizing Echo State Networks. This library is an extension and expansion of the previous library written by Reinier Maat: https://github.com/1Reinier/Reservoir
Home-page: https://github.com/blindedjoy/RcTorch-private
Author: Hayden Joy
Author-email: hnjoy@mac.com
License: Harvard
Download-URL: https://github.com/blindedjoy/RcTorch/archive/v_01.tar.gz
Keywords: Echo State Network,ESN,Reservoir Computing,Echo State Networks,Optimization,BoTorch,PyTorch,Bayesian
Platform: UNKNOWN
Classifier: Development Status :: 3 - Alpha
Classifier: Intended Audience :: Developers
Classifier: Topic :: Software Development :: Build Tools
Classifier: License :: OSI Approved :: MIT License
Classifier: Programming Language :: Python :: 3
Classifier: Programming Language :: Python :: 3.8
Classifier: Programming Language :: Python :: 3.6
License-File: LICENSE.txt
License-File: AUTHORS
Requires-Dist: numpy
Requires-Dist: scipy
Requires-Dist: paramz
Requires-Dist: datetime
Requires-Dist: pandas
Requires-Dist: seaborn
Requires-Dist: pathlib
Requires-Dist: matplotlib
Requires-Dist: llvmlite
Requires-Dist: torch
Requires-Dist: torchvision
Requires-Dist: torchaudio
Requires-Dist: gpytorch
Requires-Dist: botorch
